gpt_verse/personas/__init__.py
gpt_verse/personas/first.py
gpt_verse/personas/second.py
gpt_verse-0.1.0.dist-info/LICENSE
gpt_verse-0.1.0.dist-info/METADATA
gpt_verse-0.1.0.dist-info/WHEEL
gpt_verse-0.1.0.dist-info/RECORD
