Metadata-Version: 2.1
Name: gpt-verse
Version: 0.1.0
Summary: 
Author: Valerio Domenici
Requires-Python: >=3.12,<4.0
Classifier: Programming Language :: Python :: 3
Classifier: Programming Language :: Python :: 3.12
Requires-Dist: langchain (>=0.1.17,<0.2.0)
Requires-Dist: langchain-openai (>=0.1.6,<0.2.0)
Requires-Dist: langgraph (>=0.0.44,<0.0.45)
